itils/__init__.py
itils/cli.py
itils/constants.py
itils-0.1.0.dist-info/entry_points.txt
itils-0.1.0.dist-info/LICENSE
itils-0.1.0.dist-info/WHEEL
itils-0.1.0.dist-info/METADATA
itils-0.1.0.dist-info/RECORD
