Metadata-Version: 2.1
Name: itils
Version: 0.1.0
Summary: A Python CLI for transforming images.
Home-page: https://github.com/joaopalmeiro/itils
License: MIT
Keywords: image,imaging,cli
Author: João Palmeiro
Author-email: joaommpalmeiro@gmail.com
Requires-Python: >=3.6,<4.0
Classifier: Development Status :: 3 - Alpha
Classifier: Environment :: Console
Classifier: Intended Audience :: Developers
Classifier: Intended Audience :: Science/Research
Classifier: License :: OSI Approved :: MIT License
Classifier: Natural Language :: English
Classifier: Operating System :: OS Independent
Classifier: Programming Language :: Python :: 3
Classifier: Programming Language :: Python :: 3.6
Classifier: Programming Language :: Python :: 3.7
Classifier: Programming Language :: Python :: 3.8
Classifier: Programming Language :: Python :: 3.9
Classifier: Programming Language :: Python :: Implementation :: CPython
Classifier: Topic :: Scientific/Engineering :: Image Processing
Classifier: Topic :: Terminals
Classifier: Topic :: Utilities
Requires-Dist: Wand (>=0.6.6,<0.7.0)
Requires-Dist: halo (>=0.0.31,<0.0.32)
Requires-Dist: importlib-metadata (>=3.0,<4.0); python_version < "3.8"
Requires-Dist: plac (>=1.3.2,<2.0.0)
Project-URL: Bug Tracker, https://github.com/joaopalmeiro/itils/issues
Project-URL: Repository, https://github.com/joaopalmeiro/itils
Project-URL: Twitter, https://twitter.com/joaompalmeiro
